controme_scraper/__init__.py
controme_scraper/controller.py
controme_scraper/logging_config.py
controme_scraper/models.py
controme_scraper/parsers.py
controme_scraper/py.typed
controme_scraper/session_manager.py
controme_scraper/url_constants.py
controme_scraper/web_client.py
controme_scraper/encryption_utils/__init__.py
controme_scraper/encryption_utils/encryption_utils.py
controme_scraper-0.1.2.dist-info/licenses/LICENSE
controme_scraper-0.1.2.dist-info/METADATA
controme_scraper-0.1.2.dist-info/WHEEL
controme_scraper-0.1.2.dist-info/top_level.txt
controme_scraper-0.1.2.dist-info/RECORD
