Metadata-Version: 2.4
Name: controme-scraper
Version: 0.1.2
Summary: Python client library for Controme Smart-Heat-OS heating control systems
Author-email: Maximilian Bick <maxibick@users.noreply.github.com>
License: MIT
Project-URL: Homepage, https://github.com/m-bck/controme-scraper
Project-URL: Documentation, https://github.com/m-bck/controme-scraper#readme
Project-URL: Repository, https://github.com/m-bck/controme-scraper
Project-URL: Bug Tracker, https://github.com/m-bck/controme-scraper/issues
Keywords: controme,heating,smart-home,home-automation,api-client
Classifier: Development Status :: 4 - Beta
Classifier: Intended Audience :: Developers
Classifier: License :: OSI Approved :: MIT License
Classifier: Operating System :: OS Independent
Classifier: Programming Language :: Python :: 3
Classifier: Programming Language :: Python :: 3.10
Classifier: Programming Language :: Python :: 3.11
Classifier: Programming Language :: Python :: 3.12
Classifier: Programming Language :: Python :: 3.13
Classifier: Topic :: Home Automation
Classifier: Topic :: Software Development :: Libraries :: Python Modules
Requires-Python: >=3.10
License-File: LICENSE
Requires-Dist: requests>=2.31.0
Requires-Dist: beautifulsoup4>=4.12.0
Requires-Dist: pycryptodome>=3.19.0
Provides-Extra: dev
Requires-Dist: pytest>=7.4.0; extra == "dev"
Requires-Dist: pytest-cov>=4.1.0; extra == "dev"
Requires-Dist: black>=23.7.0; extra == "dev"
Requires-Dist: ruff>=0.0.285; extra == "dev"
Dynamic: license-file
